gitimerge.py
usr/share/bash-completion/completions/git-imerge
git_imerge-1.2.0.dist-info/COPYING
git_imerge-1.2.0.dist-info/METADATA
git_imerge-1.2.0.dist-info/WHEEL
git_imerge-1.2.0.dist-info/entry_points.txt
git_imerge-1.2.0.dist-info/top_level.txt
git_imerge-1.2.0.dist-info/RECORD
